cr_obj_naming/VERSION
cr_obj_naming/__init__.py
cr_obj_naming/__version__.py
cr_obj_naming/cnd_consul.py
cr_obj_naming/obj_naming.py
cnd_cr_obj_naming-1.0.3.dist-info/METADATA
cnd_cr_obj_naming-1.0.3.dist-info/WHEEL
cnd_cr_obj_naming-1.0.3.dist-info/top_level.txt
cnd_cr_obj_naming-1.0.3.dist-info/RECORD
