Metadata-Version: 2.1
Name: cnd-cr-obj-naming
Version: 1.0.3
Summary: Base for vro Custom Resource Object Naming
Home-page: https://gitlab.com/changendevops/cloudtools/cnd-cr-object.git
Author: Denis FABIEN
Author-email: denis.fabien@changendevops.com
License: MIT/X11
Project-URL: Documentation, https://changendevops.com
Project-URL: Source, https://gitlab.com/changendevops/cloudtools/cnd-cr-object.git
Classifier: License :: OSI Approved :: MIT License
Classifier: Operating System :: OS Independent
Requires-Dist: cndprint
Requires-Dist: pyyaml
Requires-Dist: requests
Requires-Dist: cndIo
Requires-Dist: yamale
Requires-Dist: twine
Requires-Dist: wheel
Requires-Dist: cnd-cr-object
Requires-Dist: python-consul
